unique_internal_search/config.py
unique_internal_search/prompts.py
unique_internal_search/service.py
unique_internal_search/uploaded_search/config.py
unique_internal_search/uploaded_search/prompts.py
unique_internal_search/uploaded_search/service.py
unique_internal_search/utils.py
unique_internal_search/validators.py
unique_internal_search-1.2.21.dist-info/LICENSE
unique_internal_search-1.2.21.dist-info/METADATA
unique_internal_search-1.2.21.dist-info/WHEEL
unique_internal_search-1.2.21.dist-info/RECORD
