Metadata-Version: 2.1
Name: unique_internal_search
Version: 1.2.21
Summary: 
License: Proprietary
Author: Martin Fadler
Author-email: martin.fadler@unique.ch
Requires-Python: >=3.12,<4.0
Classifier: License :: Other/Proprietary License
Classifier: Programming Language :: Python :: 3
Classifier: Programming Language :: Python :: 3.12
Requires-Dist: pydantic (>=2.8.2,<3.0.0)
Requires-Dist: typing-extensions (>=4.9.0,<5.0.0)
Requires-Dist: unique-toolkit (>=1.42.9,<2.0.0)
